{"Cities": [{"coord":{"lon":48.02861,"lat":29.332781},"name":"Ḩawallī","id":285629},{"coord":{"lon":47.663891,"lat":29.31583},"name":"\u2018Ushaysh al Jahrā\u2019","id":285375},{"coord":{"lon":48.001389,"lat":29.365},"name":"Ad Dasmah","id":285856},{"coord":{"lon":47.93111,"lat":29.25028},"name":"Al \u2018Abbāsīyah","id":388088},{"coord":{"lon":48.083889,"lat":29.076941},"name":"Al Aḩmadī","id":285839},{"coord":{"lon":48.086941,"lat":29.3025},"name":"Al Bida\u2018","id":285822},{"coord":{"lon":48.13028,"lat":29.0825},"name":"Al Fahahil","id":285811},{"coord":{"lon":47.958611,"lat":29.2775},"name":"Al Farwaniyah","id":285815},{"coord":{"lon":48.121109,"lat":29.173889},"name":"Al Fintas","id":285812},{"coord":{"lon":48.101669,"lat":29.225281},"name":"Al Funaytis","id":285810},{"coord":{"lon":47.658058,"lat":29.3375},"name":"Al Jahra","id":285799},{"coord":{"lon":48.13028,"lat":29.145},"name":"Al Mahbulah","id":285782},{"coord":{"lon":48.132778,"lat":29.096109},"name":"Al Manqaf","id":285778},{"coord":{"lon":47.971668,"lat":29.37361},"name":"Al Qiblah","id":387990},{"coord":{"lon":48.053059,"lat":28.554171},"name":"Al Wafrah","id":387897},{"coord":{"lon":47.930561,"lat":28.63917},"name":"Al Wafrah","id":285760},{"coord":{"lon":48.075829,"lat":29.246389},"name":"An Nijfah","id":285747},{"coord":{"lon":47.93306,"lat":29.295},"name":"Ar Rabiyah","id":388065},{"coord":{"lon":48.094719,"lat":29.14583},"name":"Ar Riqqah","id":285728},{"coord":{"lon":48.076111,"lat":29.333891},"name":"As Salimiyah","id":285704},{"coord":{"lon":47.96167,"lat":29.347219},"name":"Ash Shamiyah","id":285721},{"coord":{"lon":48.274719,"lat":29.442499},"name":"Az Zawr","id":285673},{"coord":{"lon":48.048809,"lat":29.3032},"name":"Bayan","id":285663},{"coord":{"lon":47.651798,"lat":29.384199},"name":"Highway of Death","id":6942029},{"coord":{"lon":47.978062,"lat":29.269171},"name":"Janub as Surrah","id":285603},{"coord":{"lon":47.978329,"lat":29.36972},"name":"Kuwait City","id":285787},{"coord":{"lon":47.997219,"lat":29.283331},"name":"Muḩāfaz̧at Ḩawallī","id":285628},{"coord":{"lon":47.916672,"lat":29.33333},"name":"Muḩāfaz̧at al \u2018Āşimah","id":285788},{"coord":{"lon":48,"lat":29},"name":"Muḩāfaz̧at al Aḩmadī","id":285841},{"coord":{"lon":47.666672,"lat":29.33333},"name":"Muḩāfaz̧at Jahrā\u2019","id":285798},{"coord":{"lon":48.05722,"lat":29.257219},"name":"Sabah as Salim","id":412800},{"coord":{"lon":48.078609,"lat":29.29583},"name":"Salwa","id":387958},{"coord":{"lon":47.75,"lat":29.5},"name":"State of Kuwait","id":285570}]}
