{"Cities": [{"coord":{"lon":12.4185,"lat":43.94593},"name":"Acquaviva","id":3183500},{"coord":{"lon":12.44738,"lat":43.941929},"name":"Borgo Maggiore","id":3181793},{"coord":{"lon":12.45,"lat":43.933331},"name":"Castello di San Marino Città","id":3345302},{"coord":{"lon":12.47008,"lat":43.952789},"name":"Domagnano","id":3177542},{"coord":{"lon":12.49798,"lat":43.92831},"name":"Faetano","id":3177299},{"coord":{"lon":12.45738,"lat":43.910011},"name":"Fiorentino","id":3176966},{"coord":{"lon":12.48201,"lat":43.908779},"name":"Monte Giardino","id":3172906},{"coord":{"lon":12.42142,"lat":43.90451},"name":"Poggio di Chiesanuova","id":3170472},{"coord":{"lon":12.41667,"lat":43.933331},"name":"Repubblica di San Marino","id":3168068},{"coord":{"lon":12.45,"lat":43.933331},"name":"San Marino","id":3168070},{"coord":{"lon":12.43858,"lat":43.93388},"name":"Santa Mustiola","id":8199069},{"coord":{"lon":12.48167,"lat":43.968971},"name":"Serravalle","id":3166645}]}
